setup.py
botanio/__init__.py
botanio/botan.py
botanio/test.py
botanio.egg-info/PKG-INFO
botanio.egg-info/SOURCES.txt
botanio.egg-info/dependency_links.txt
botanio.egg-info/not-zip-safe
botanio.egg-info/requires.txt
botanio.egg-info/top_level.txt