Metadata-Version: 1.0
Name: botanio
Version: 1.0.0
Summary: Botan SDK: Advanced analytics for your Telegram bot
Home-page: https://github.com/botanio/sdk
Author: Botan.io team
Author-email: team@botan.io
License: MIT
Platform: UNKNOWN
